pytest_testrail_api_client/__init__.py
pytest_testrail_api_client/configure.py
pytest_testrail_api_client/service.py
pytest_testrail_api_client/test_rail.py
pytest_testrail_api_client/validate.py
pytest_testrail_api_client/api/__init__.py
pytest_testrail_api_client/api/cases_api.py
pytest_testrail_api_client/api/congif_api.py
pytest_testrail_api_client/api/milestones_api.py
pytest_testrail_api_client/api/plans_api.py
pytest_testrail_api_client/api/project_api.py
pytest_testrail_api_client/api/results_api.py
pytest_testrail_api_client/api/runs_api.py
pytest_testrail_api_client/api/sections_api.py
pytest_testrail_api_client/api/service_api.py
pytest_testrail_api_client/api/small_api.py
pytest_testrail_api_client/api/suites_api.py
pytest_testrail_api_client/api/user_api.py
pytest_testrail_api_client/modules/__init__.py
pytest_testrail_api_client/modules/bdd_classes.py
pytest_testrail_api_client/modules/case.py
pytest_testrail_api_client/modules/case_field.py
pytest_testrail_api_client/modules/category.py
pytest_testrail_api_client/modules/classes.py
pytest_testrail_api_client/modules/config_obj.py
pytest_testrail_api_client/modules/exceptions.py
pytest_testrail_api_client/modules/plan.py
pytest_testrail_api_client/modules/result.py
pytest_testrail_api_client/modules/session.py
pytest_testrail_api_client/modules/results/__init__.py
pytest_testrail_api_client-0.3.9.dist-info/LICENSE
pytest_testrail_api_client-0.3.9.dist-info/METADATA
pytest_testrail_api_client-0.3.9.dist-info/WHEEL
pytest_testrail_api_client-0.3.9.dist-info/entry_points.txt
pytest_testrail_api_client-0.3.9.dist-info/top_level.txt
pytest_testrail_api_client-0.3.9.dist-info/RECORD
